LICENSE
README.md
setup.py
saturno/__init__.py
saturno/anime.py
saturno/config.json
saturno/manage.py
saturno/saturno.py
saturno.egg-info/PKG-INFO
saturno.egg-info/SOURCES.txt
saturno.egg-info/dependency_links.txt
saturno.egg-info/entry_points.txt
saturno.egg-info/requires.txt
saturno.egg-info/top_level.txt