Metadata-Version: 2.1
Name: saturno
Version: 1.9.2
Summary: A python module to download anime from Anime Saturn
Home-page: https://github.com/mortafix/Saturno
Author: Moris Doratiotto
Author-email: moris.doratiotto@gmail.com
License: UNKNOWN
Keywords: anime,saturn,download
Platform: UNKNOWN
Classifier: Programming Language :: Python :: 3.8
Classifier: License :: OSI Approved :: MIT License
Classifier: Operating System :: OS Independent
Classifier: Development Status :: 3 - Alpha
Classifier: Intended Audience :: Developers
Requires-Python: >=3.8
License-File: LICENSE
